base16/__init__.py
base16/__main__.py
base16/base16.py
base16-0.1.2.dist-info/LICENSE
base16-0.1.2.dist-info/METADATA
base16-0.1.2.dist-info/WHEEL
base16-0.1.2.dist-info/entry_points.txt
base16-0.1.2.dist-info/top_level.txt
base16-0.1.2.dist-info/RECORD
