Metadata-Version: 2.1
Name: base16
Version: 0.1.2
Summary: base16 is like hexadecimal, but with an alphabet chosen to minimise human transcription errors.
Home-page: https://www.github.com/philiporange/base16
Author: Philip Orange
Classifier: License :: CC0 1.0 Universal (CC0 1.0) Public Domain Dedication
Classifier: Programming Language :: Python :: 3
Classifier: Operating System :: OS Independent
Classifier: Topic :: Utilities
License-File: LICENSE
